mini_ode-0.1.4.dist-info/METADATA
mini_ode-0.1.4.dist-info/WHEEL
mini_ode/__init__.py
mini_ode/__pycache__/__init__.cpython-313.pyc
mini_ode/__pycache__/__init__.cpython-314.pyc
mini_ode/__pycache__/optimizers.cpython-313.pyc
mini_ode/__pycache__/optimizers.cpython-314.pyc
mini_ode/optimizers.py
mini_ode/py.typed
mini_ode/rust.abi3.so
mini_ode/rust.pyi
mini_ode-0.1.4.dist-info/RECORD
